imouse/__init__.py
imouse/imouse_types.py
imouse/api/__init__.py
imouse/api/console/__init__.py
imouse/api/console/airplay.py
imouse/api/console/config.py
imouse/api/console/device.py
imouse/api/console/group.py
imouse/api/console/usb.py
imouse/api/console/user.py
imouse/api/device/__init__.py
imouse/api/device/command.py
imouse/api/device/image.py
imouse/api/device/keyboard.py
imouse/api/device/mouse.py
imouse/api/device/shortcut.py
imouse/legacy_api/__init__.py
imouse/legacy_api/config.py
imouse/legacy_api/device.py
imouse/legacy_api/mouse_key.py
imouse/legacy_api/pic.py
imouse/legacy_api/shortcut.py
imouse/legacy_api/user.py
imouse/models/__init__.py
imouse/models/response.py
imouse/shared/base_api.py
imouse/shared/client.py
imouse/shared/event_dispatcher.py
imouse/shared/payload.py
imouse/utils/__init__.py
imouse/utils/logger.py
imouse/utils/utils.py
py_imouse_xp-1.0.1.dist-info/licenses/LICENSE
py_imouse_xp-1.0.1.dist-info/METADATA
py_imouse_xp-1.0.1.dist-info/WHEEL
py_imouse_xp-1.0.1.dist-info/top_level.txt
py_imouse_xp-1.0.1.dist-info/RECORD
